Metadata-Version: 1.1
Name: grape-pipeline
Version: 2.0-alpha.3
Summary: The Grape RNASeq pipeline version 2
Home-page: https://grape-pipeline.org/
Author: Emilio Palumbo, Thasso Griebel
Author-email: UNKNOWN
License: GNU General Public License (GPL)
Platform: lx64
Classifier: Development Status :: 3 - Alpha
Classifier: Environment :: Console
Classifier: Intended Audience :: End Users/Desktop
Classifier: Intended Audience :: Developers
Classifier: License :: OSI Approved :: GNU General Public License (GPL)
Classifier: Operating System :: POSIX :: Linux
Classifier: Programming Language :: Python
Classifier: Topic :: Scientific/Engineering :: Bio-Informatics
